[
    {
        "OrderID": 1760568256,
        "Subtotal": 51171499444.1717
    },
    {
        "OrderID": 1356967724,
        "Subtotal": 99894194887.0196
    },
    {
        "OrderID": 196751057,
        "Subtotal": 93603156390.5999
    },
    {
        "OrderID": 1019555008,
        "Subtotal": 59696277370.6763
    },
    {
        "OrderID": 228532880,
        "Subtotal": 21974882786.1621
    },
    {
        "OrderID": 796484036,
        "Subtotal": 2366822795.0111
    },
    {
        "OrderID": 1359982424,
        "Subtotal": 20548992743.7156
    },
    {
        "OrderID": 1637702692,
        "Subtotal": 9937388263.6427
    },
    {
        "OrderID": 1095082235,
        "Subtotal": 95015081460.5876
    },
    {
        "OrderID": 899284961,
        "Subtotal": 41115755517.967
    },
    {
        "OrderID": 1935851112,
        "Subtotal": 71339737228.1178
    },
    {
        "OrderID": 190287189,
        "Subtotal": 32351470412.6864
    },
    {
        "OrderID": 1177135869,
        "Subtotal": 16771889873.7803
    },
    {
        "OrderID": 1319973437,
        "Subtotal": 24788966076.4485
    },
    {
        "OrderID": 585192200,
        "Subtotal": 52287231292.5755
    },
    {
        "OrderID": 1356997654,
        "Subtotal": 89121120213.5309
    },
    {
        "OrderID": 6924324,
        "Subtotal": 21929328702.3901
    },
    {
        "OrderID": 55717736,
        "Subtotal": 82038058387.1155
    },
    {
        "OrderID": 612688067,
        "Subtotal": 93221877468.7498
    },
    {
        "OrderID": 121720582,
        "Subtotal": 16563353920.3554
    },
    {
        "OrderID": 2084449300,
        "Subtotal": 66249140887.5212
    },
    {
        "OrderID": 755894064,
        "Subtotal": 33296279027.1267
    },
    {
        "OrderID": 689884090,
        "Subtotal": 52682211808.8602
    },
    {
        "OrderID": 1614707074,
        "Subtotal": 63509798306.0404
    },
    {
        "OrderID": 1443986012,
        "Subtotal": 68234815541.6548
    },
    {
        "OrderID": 1300014450,
        "Subtotal": 64655493060.1268
    },
    {
        "OrderID": 1262169203,
        "Subtotal": 25329178804.5316
    },
    {
        "OrderID": 1393291621,
        "Subtotal": 20491940272.0406
    },
    {
        "OrderID": 1285720304,
        "Subtotal": 15620841830.9688
    },
    {
        "OrderID": 1592467755,
        "Subtotal": 71086280141.0257
    },
    {
        "OrderID": 1623431843,
        "Subtotal": 23688447149.4704
    },
    {
        "OrderID": 596204959,
        "Subtotal": 61664970591.6643
    },
    {
        "OrderID": 595854520,
        "Subtotal": 2907148282.9749
    },
    {
        "OrderID": 646411676,
        "Subtotal": 94559120223.8574
    },
    {
        "OrderID": 1668934663,
        "Subtotal": 35173232504.1666
    },
    {
        "OrderID": 545719406,
        "Subtotal": 73735659592.7849
    },
    {
        "OrderID": 397221504,
        "Subtotal": 45852890308.015
    },
    {
        "OrderID": 1639702407,
        "Subtotal": 85128324525.4307
    },
    {
        "OrderID": 808842805,
        "Subtotal": 45029098982.9227
    },
    {
        "OrderID": 867290412,
        "Subtotal": 40336760040.3726
    },
    {
        "OrderID": 602020658,
        "Subtotal": 36890759761.4452
    },
    {
        "OrderID": 383729865,
        "Subtotal": 40901272697.3742
    },
    {
        "OrderID": 871167767,
        "Subtotal": 56622152612.5445
    },
    {
        "OrderID": 774720516,
        "Subtotal": 68634572089.6497
    },
    {
        "OrderID": 192129755,
        "Subtotal": 99485961184.8369
    },
    {
        "OrderID": 1412830249,
        "Subtotal": 31546400836.6689
    },
    {
        "OrderID": 618019369,
        "Subtotal": 5145297129.6384
    },
    {
        "OrderID": 1447251900,
        "Subtotal": 80394298350.4384
    },
    {
        "OrderID": 1001172049,
        "Subtotal": 43217723490.6703
    },
    {
        "OrderID": 2134535724,
        "Subtotal": 38057043426.6701
    },
    {
        "OrderID": 2116062822,
        "Subtotal": 38734428188.7635
    },
    {
        "OrderID": 689137825,
        "Subtotal": 48735109693.3707
    },
    {
        "OrderID": 930716821,
        "Subtotal": 5304064974.1888
    },
    {
        "OrderID": 808096729,
        "Subtotal": 62246978376.0607
    },
    {
        "OrderID": 1276741092,
        "Subtotal": 25900512025.6915
    },
    {
        "OrderID": 336353350,
        "Subtotal": 58049018750.8985
    },
    {
        "OrderID": 779208837,
        "Subtotal": 39001497835.8522
    },
    {
        "OrderID": 404337984,
        "Subtotal": 16272942326.0316
    },
    {
        "OrderID": 1719398755,
        "Subtotal": 86387969250.7907
    },
    {
        "OrderID": 107976239,
        "Subtotal": 23228034516.7964
    },
    {
        "OrderID": 622045850,
        "Subtotal": 906565296.4636
    },
    {
        "OrderID": 1893078953,
        "Subtotal": 3931805840.6934
    },
    {
        "OrderID": 1701215621,
        "Subtotal": 40678510908.0374
    },
    {
        "OrderID": 288039618,
        "Subtotal": 97975176014.0061
    },
    {
        "OrderID": 489643271,
        "Subtotal": 11236151866.6148
    },
    {
        "OrderID": 1590026995,
        "Subtotal": 19359651207.9238
    },
    {
        "OrderID": 407657551,
        "Subtotal": 71776097314.4322
    },
    {
        "OrderID": 678329129,
        "Subtotal": 8276400645.2634
    },
    {
        "OrderID": 107124005,
        "Subtotal": 60143245174.5495
    },
    {
        "OrderID": 970988009,
        "Subtotal": 73942201165.4823
    },
    {
        "OrderID": 49228216,
        "Subtotal": 32428325433.284
    },
    {
        "OrderID": 52124332,
        "Subtotal": 85330603155.3074
    },
    {
        "OrderID": 302769069,
        "Subtotal": 88458693772.5543
    },
    {
        "OrderID": 1115012403,
        "Subtotal": 37352462136.1866
    },
    {
        "OrderID": 1710546300,
        "Subtotal": 17121894401.4981
    },
    {
        "OrderID": 2117552119,
        "Subtotal": 13807265413.925
    },
    {
        "OrderID": 979457798,
        "Subtotal": 22831591567.9559
    },
    {
        "OrderID": 2033363139,
        "Subtotal": 34171585226.4314
    },
    {
        "OrderID": 2122476422,
        "Subtotal": 88502893620.1706
    },
    {
        "OrderID": 271472753,
        "Subtotal": 78310785139.9108
    },
    {
        "OrderID": 1857763336,
        "Subtotal": 69466902967.5424
    },
    {
        "OrderID": 345829115,
        "Subtotal": 23575490992.5162
    },
    {
        "OrderID": 1379898694,
        "Subtotal": 57696556183.5095
    },
    {
        "OrderID": 1429838543,
        "Subtotal": 17677750927.3961
    },
    {
        "OrderID": 1531772672,
        "Subtotal": 12058680178.5975
    },
    {
        "OrderID": 1886414689,
        "Subtotal": 32328463625.1628
    },
    {
        "OrderID": 505043602,
        "Subtotal": 45967771857.9769
    },
    {
        "OrderID": 4747334,
        "Subtotal": 74798528454.2664
    },
    {
        "OrderID": 617426188,
        "Subtotal": 78230307064.9504
    },
    {
        "OrderID": 1733262913,
        "Subtotal": 23569714208.1335
    },
    {
        "OrderID": 1651632425,
        "Subtotal": 41053868853.487
    },
    {
        "OrderID": 1460767386,
        "Subtotal": 50368985952.8094
    },
    {
        "OrderID": 360898699,
        "Subtotal": 33796262997.2025
    },
    {
        "OrderID": 1224175824,
        "Subtotal": 84353310009.4646
    },
    {
        "OrderID": 231601452,
        "Subtotal": 43912593252.0255
    },
    {
        "OrderID": 174967259,
        "Subtotal": 6174960965.2906
    },
    {
        "OrderID": 1414603567,
        "Subtotal": 61778733134.2697
    },
    {
        "OrderID": 47603802,
        "Subtotal": 26701774401.5902
    },
    {
        "OrderID": 355182561,
        "Subtotal": 68897558772.0051
    },
    {
        "OrderID": 698314370,
        "Subtotal": 54685224383.1381
    },
    {
        "OrderID": 986630981,
        "Subtotal": 1640206133.0154
    },
    {
        "OrderID": 474964369,
        "Subtotal": 83013636781.834
    },
    {
        "OrderID": 2117444844,
        "Subtotal": 44090367876.9245
    },
    {
        "OrderID": 1287506048,
        "Subtotal": 19288320466.876
    },
    {
        "OrderID": 901186880,
        "Subtotal": 38023255974.9856
    },
    {
        "OrderID": 681119592,
        "Subtotal": 13495594030.2461
    },
    {
        "OrderID": 1502702194,
        "Subtotal": 61147024179.8087
    },
    {
        "OrderID": 199182093,
        "Subtotal": 84513457608.4092
    },
    {
        "OrderID": 49567996,
        "Subtotal": 70849283318.9666
    },
    {
        "OrderID": 1377782105,
        "Subtotal": 76346604130.2308
    },
    {
        "OrderID": 1618485815,
        "Subtotal": 35525793838.3147
    },
    {
        "OrderID": 635186412,
        "Subtotal": 64109092927.5378
    },
    {
        "OrderID": 1959745859,
        "Subtotal": 40185739705.339
    },
    {
        "OrderID": 290365037,
        "Subtotal": 23090862971.7305
    },
    {
        "OrderID": 1511611183,
        "Subtotal": 64750008331.6117
    },
    {
        "OrderID": 94695685,
        "Subtotal": 79079564847.052
    },
    {
        "OrderID": 2016913736,
        "Subtotal": 58143173390.9994
    },
    {
        "OrderID": 1470093503,
        "Subtotal": 89427389693.4464
    },
    {
        "OrderID": 1045840631,
        "Subtotal": 84537464100.8675
    },
    {
        "OrderID": 1565485009,
        "Subtotal": 65831272350.6242
    },
    {
        "OrderID": 344101250,
        "Subtotal": 33784226863.645
    },
    {
        "OrderID": 1262967755,
        "Subtotal": 7953824731.5213
    },
    {
        "OrderID": 1759217390,
        "Subtotal": 52328153862.6179
    },
    {
        "OrderID": 1057043353,
        "Subtotal": 49972291872.8366
    },
    {
        "OrderID": 1274057652,
        "Subtotal": 42070305394.0087
    },
    {
        "OrderID": 287320027,
        "Subtotal": 21975897485.3903
    },
    {
        "OrderID": 1473729177,
        "Subtotal": 1277165417.5594
    },
    {
        "OrderID": 1086772086,
        "Subtotal": 80227094190.1951
    },
    {
        "OrderID": 1322751363,
        "Subtotal": 19927584100.5146
    },
    {
        "OrderID": 1631845296,
        "Subtotal": 41707309591.5839
    },
    {
        "OrderID": 1824082375,
        "Subtotal": 88097658380.866
    },
    {
        "OrderID": 1473066222,
        "Subtotal": 48642027727.3282
    },
    {
        "OrderID": 1915979472,
        "Subtotal": 46658965526.1486
    },
    {
        "OrderID": 1770034709,
        "Subtotal": 69311059126.6304
    },
    {
        "OrderID": 1027954321,
        "Subtotal": 4554055235.3486
    },
    {
        "OrderID": 1074245780,
        "Subtotal": 53086783597.2458
    },
    {
        "OrderID": 648901098,
        "Subtotal": 13995413621.8875
    },
    {
        "OrderID": 587317641,
        "Subtotal": 84737053350.5454
    },
    {
        "OrderID": 1384997329,
        "Subtotal": 94242772459.9838
    },
    {
        "OrderID": 607346603,
        "Subtotal": 52095654327.4223
    },
    {
        "OrderID": 1371350125,
        "Subtotal": 43918438954.2788
    },
    {
        "OrderID": 617121859,
        "Subtotal": 50432659499.3472
    },
    {
        "OrderID": 2063167087,
        "Subtotal": 70728896209.0387
    },
    {
        "OrderID": 988217990,
        "Subtotal": 92583747301.2506
    },
    {
        "OrderID": 781522561,
        "Subtotal": 95337749295.8679
    },
    {
        "OrderID": 534355016,
        "Subtotal": 46399990422.6511
    },
    {
        "OrderID": 1771870118,
        "Subtotal": 91538283345.2895
    },
    {
        "OrderID": 1741174740,
        "Subtotal": 50545112369.582
    },
    {
        "OrderID": 157353807,
        "Subtotal": 31993948132.731
    },
    {
        "OrderID": 1821132952,
        "Subtotal": 35773352836.2587
    },
    {
        "OrderID": 905268492,
        "Subtotal": 38087978307.1577
    },
    {
        "OrderID": 253906143,
        "Subtotal": 85512200393.714
    },
    {
        "OrderID": 1281992847,
        "Subtotal": 72006242140.1962
    },
    {
        "OrderID": 1191958576,
        "Subtotal": 60870531457.4763
    },
    {
        "OrderID": 1425006650,
        "Subtotal": 83612893428.6534
    },
    {
        "OrderID": 2134203589,
        "Subtotal": 13463163143.0238
    },
    {
        "OrderID": 1834430967,
        "Subtotal": 80502343876.2873
    },
    {
        "OrderID": 777334848,
        "Subtotal": 35717701120.302
    },
    {
        "OrderID": 1573797895,
        "Subtotal": 5185674806.1254
    },
    {
        "OrderID": 2118385073,
        "Subtotal": 13637307239.6963
    },
    {
        "OrderID": 1709438768,
        "Subtotal": 26417281175.9635
    },
    {
        "OrderID": 1500006216,
        "Subtotal": 55755320400.9309
    },
    {
        "OrderID": 1688023009,
        "Subtotal": 81171093927.6963
    },
    {
        "OrderID": 1110240569,
        "Subtotal": 51340634096.4138
    },
    {
        "OrderID": 1996750228,
        "Subtotal": 53698708536.1033
    },
    {
        "OrderID": 2064657169,
        "Subtotal": 94237281498.4992
    },
    {
        "OrderID": 1843280400,
        "Subtotal": 57939926767.7217
    },
    {
        "OrderID": 1623792965,
        "Subtotal": 76916087279.0962
    },
    {
        "OrderID": 867459159,
        "Subtotal": 93922972702.4212
    },
    {
        "OrderID": 709637072,
        "Subtotal": 60059465770.6096
    },
    {
        "OrderID": 702863380,
        "Subtotal": 16257880697.9581
    },
    {
        "OrderID": 139206970,
        "Subtotal": 61039874958.8057
    },
    {
        "OrderID": 2030614192,
        "Subtotal": 62373292772.0993
    },
    {
        "OrderID": 283407280,
        "Subtotal": 42309302021.7493
    },
    {
        "OrderID": 1782437788,
        "Subtotal": 34490994620.1369
    },
    {
        "OrderID": 464672829,
        "Subtotal": 49728667526.5058
    },
    {
        "OrderID": 527449291,
        "Subtotal": 72437827289.1044
    },
    {
        "OrderID": 1525658948,
        "Subtotal": 86509002465.7547
    },
    {
        "OrderID": 1763471919,
        "Subtotal": 26906185294.5014
    },
    {
        "OrderID": 1211082718,
        "Subtotal": 3845787956.3793
    },
    {
        "OrderID": 959643043,
        "Subtotal": 99758333805.9484
    },
    {
        "OrderID": 1758304628,
        "Subtotal": 72966370545.3276
    },
    {
        "OrderID": 1060246179,
        "Subtotal": 47369956132.0245
    },
    {
        "OrderID": 681878176,
        "Subtotal": 28139443183.3177
    },
    {
        "OrderID": 1341468317,
        "Subtotal": 17314745835.0285
    },
    {
        "OrderID": 1779027079,
        "Subtotal": 42801512265.5779
    },
    {
        "OrderID": 551819341,
        "Subtotal": 35188707592.8971
    },
    {
        "OrderID": 1877952551,
        "Subtotal": 84021273627.8772
    },
    {
        "OrderID": 336975871,
        "Subtotal": 85584846860.7291
    },
    {
        "OrderID": 196855628,
        "Subtotal": 81340619595.7213
    },
    {
        "OrderID": 1776941574,
        "Subtotal": 20710120908.9159
    },
    {
        "OrderID": 349251582,
        "Subtotal": 51880374155.0072
    },
    {
        "OrderID": 1948017606,
        "Subtotal": 39198361919.2615
    },
    {
        "OrderID": 1324244490,
        "Subtotal": 7166130212.1356
    },
    {
        "OrderID": 1459137333,
        "Subtotal": 68844272964.6339
    },
    {
        "OrderID": 1078162539,
        "Subtotal": 39818029268.6447
    },
    {
        "OrderID": 1777696394,
        "Subtotal": 78316295542.7542
    },
    {
        "OrderID": 532449544,
        "Subtotal": 23296258342.4523
    },
    {
        "OrderID": 1971344093,
        "Subtotal": 27811831678.2638
    },
    {
        "OrderID": 1624529060,
        "Subtotal": 66596274916.0826
    }
]